cmsplugin_section_ai/__init__.py
cmsplugin_section_ai/cms_plugins.py
cmsplugin_section_ai/enums.py
cmsplugin_section_ai/models.py
cmsplugin_section_ai/migrations/0001_initial.py
cmsplugin_section_ai/migrations/0002_full_refactor_of_fields.py
cmsplugin_section_ai/migrations/__init__.py
cmsplugin_section_ai/templates/cmsplugin_section_ai/section.html
cmsplugin_section_ai/templates/cmsplugin_section_ai/includes/_section_button.html
cmsplugin_section_ai/templates/cmsplugin_section_ai/includes/_section_content.html
cmsplugin_section_ai/templates/cmsplugin_section_ai/includes/_section_title.html
cmsplugin_section_ai-0.1.0.dist-info/DESCRIPTION.rst
cmsplugin_section_ai-0.1.0.dist-info/LICENSE.txt
cmsplugin_section_ai-0.1.0.dist-info/METADATA
cmsplugin_section_ai-0.1.0.dist-info/RECORD
cmsplugin_section_ai-0.1.0.dist-info/WHEEL
cmsplugin_section_ai-0.1.0.dist-info/metadata.json
cmsplugin_section_ai-0.1.0.dist-info/top_level.txt
