Metadata-Version: 2.0
Name: cmsplugin-section-ai
Version: 0.1.0
Summary: Django CMS Section Plugin
Home-page: https://github.com/andersinno/cmsplugin-section-ai
Author: Anders Innovations
Author-email: support@anders.fi
License: MIT
Download-URL: https://github.com/andersinno/cmsplugin-section-ai/releases
Keywords: django,section,cmsplugin
Platform: UNKNOWN
Requires-Dist: django
Requires-Dist: django-cms
Requires-Dist: django-enumfields
Requires-Dist: django-filer
